aegis/__init__.py
aegis/cleanup.py
aegis/cli.py
aegis/predictor.py
aegis_detect-0.1.6.dist-info/licenses/LICENSE
aegis_detect-0.1.6.dist-info/METADATA
aegis_detect-0.1.6.dist-info/WHEEL
aegis_detect-0.1.6.dist-info/entry_points.txt
aegis_detect-0.1.6.dist-info/top_level.txt
aegis_detect-0.1.6.dist-info/RECORD
