Metadata-Version: 2.4
Name: aegis-detect
Version: 0.1.6
Summary: AI Code Classifier Tool
Requires-Python: >=3.10
License-File: LICENSE
Requires-Dist: huggingface-hub>=0.15.0
Requires-Dist: numpy>=1.21.0
Requires-Dist: peft>=0.4.0
Requires-Dist: safetensors>=0.3.0
Requires-Dist: torch>=2.0.0
Requires-Dist: transformers>=4.30.0
Provides-Extra: dev
Requires-Dist: accelerate>=0.20.0; extra == "dev"
Requires-Dist: datasets>=2.0.0; extra == "dev"
Requires-Dist: matplotlib>=3.5.0; extra == "dev"
Requires-Dist: openai>=1.0.0; extra == "dev"
Requires-Dist: pandas>=1.5.0; extra == "dev"
Requires-Dist: python-dotenv>=0.19.0; extra == "dev"
Requires-Dist: scikit-learn>=1.0.0; extra == "dev"
Requires-Dist: seaborn>=0.13.2; extra == "dev"
Requires-Dist: tqdm>=4.60.0; extra == "dev"
Provides-Extra: all
Requires-Dist: aegis-detect[dev]; extra == "all"
Dynamic: license-file
